examples/packages/foo/_beacons/test_beacon.py
examples/packages/foo/_clouds/test_cloud.py
examples/packages/foo/_engines/test_engine.py
examples/packages/foo/_executors/test_executor.py
examples/packages/foo/_grains/test_grain.py
examples/packages/foo/_log_handlers/test_log_handler.py
examples/packages/foo/_matchers/test_matcher.py
examples/packages/foo/_modules/test_module.py
examples/packages/foo/_output/test_output.py
examples/packages/foo/_pillar/test_pillar.py
examples/packages/foo/_proxymodules/test_proxy.py
examples/packages/foo/_renderers/test_renderer.py
examples/packages/foo/_returners/test_returner.py
examples/packages/foo/_sdb/test_sdb.py
examples/packages/foo/_serializers/test_serializer.py
examples/packages/foo/_states/test_state.py
examples/packages/foo/_thorium/test_thorium.py
examples/packages/foo/_tops/test_top.py
examples/packages/foo/_utils/test_utils.py
salt_bundle/__init__.py
salt_bundle/__main__.py
salt_bundle/cli.py
salt_bundle/config.py
salt_bundle/github.py
salt_bundle/lockfile.py
salt_bundle/package.py
salt_bundle/release.py
salt_bundle/repository.py
salt_bundle/resolver.py
salt_bundle/vendor.py
salt_bundle/cli/__init__.py
salt_bundle/cli/formula/__init__.py
salt_bundle/cli/formula/init.py
salt_bundle/cli/formula/pack.py
salt_bundle/cli/formula/sync.py
salt_bundle/cli/formula/verify.py
salt_bundle/cli/project/__init__.py
salt_bundle/cli/project/init.py
salt_bundle/cli/project/install.py
salt_bundle/cli/project/update.py
salt_bundle/cli/project/vendor.py
salt_bundle/cli/repo/__init__.py
salt_bundle/cli/repo/add.py
salt_bundle/cli/repo/index.py
salt_bundle/cli/repo/release.py
salt_bundle/ext/__init__.py
salt_bundle/ext/loader.py
salt_bundle/ext/fileserver/__init__.py
salt_bundle/ext/fileserver/bundlefs.py
salt_bundle/ext/pillar/__init__.py
salt_bundle/ext/pillar/saltbundle.py
salt_bundle/models/__init__.py
salt_bundle/models/config_models.py
salt_bundle/models/index_models.py
salt_bundle/models/lock_models.py
salt_bundle-1.0.3.dist-info/METADATA
salt_bundle-1.0.3.dist-info/WHEEL
salt_bundle-1.0.3.dist-info/entry_points.txt
salt_bundle-1.0.3.dist-info/top_level.txt
salt_bundle-1.0.3.dist-info/RECORD
