Metadata-Version: 2.4
Name: salt-bundle
Version: 1.0.3
Summary: Salt package manager prototype
Requires-Python: >=3.10
Requires-Dist: click
Requires-Dist: pydantic>=2.0.0
Requires-Dist: pyyaml
Requires-Dist: semver>=3.0.0
Requires-Dist: requests
Requires-Dist: PyGithub>=2.0.0
